potator
