Metadata-Version: 2.1
Name: potator
Version: 0.1.1
Summary: UNKNOWN
Home-page: https://github.com/otzhora/potator
Author: Yuriy Rogachev
Author-email: rogachev.yuiry28@gmail.com
License: MIT
Download-URL: https://github.com/otzhora/potator/releases/tag/v0.1.1
Keywords: STATIC-ANALYSIS,PLAGIARISM-DETECTION,PLAGIARISM-DETECTOR
Platform: UNKNOWN
Classifier: Development Status :: 3 - Alpha
Classifier: Intended Audience :: Developers
Classifier: Topic :: Software Development :: Quality Assurance
Classifier: License :: OSI Approved :: MIT License
Classifier: Programming Language :: Python :: 3
Classifier: Programming Language :: Python :: 3.6
Classifier: Programming Language :: Python :: 3.7
Classifier: Programming Language :: Python :: 3.8
Requires-Python: >=3.6
